server.py
choumine_add-0.1.5.dist-info/METADATA
choumine_add-0.1.5.dist-info/WHEEL
choumine_add-0.1.5.dist-info/entry_points.txt
choumine_add-0.1.5.dist-info/top_level.txt
choumine_add-0.1.5.dist-info/RECORD
