Metadata-Version: 2.4
Name: choumine-add
Version: 0.1.5
Summary: choumine-add project description
Requires-Python: >=3.13
Requires-Dist: mcp[cli]>=1.6.0
